src/__init__.py
src/url_checker.py
src/url_class.py
tests/__init__.py
tests/url_machine_test.py
UrlAutomationMachine-1.0.2.dist-info/METADATA
UrlAutomationMachine-1.0.2.dist-info/WHEEL
UrlAutomationMachine-1.0.2.dist-info/entry_points.txt
UrlAutomationMachine-1.0.2.dist-info/top_level.txt
UrlAutomationMachine-1.0.2.dist-info/RECORD
