Metadata-Version: 2.1
Name: UrlAutomationMachine
Version: 1.0.2
Summary: A CMD tool designed to check the status codes of urls
Home-page: https://www.github.com/HyperTHD/URLAutomationMachine
Author: Abdulbasid Guled
Author-email: aguled5@myseneca.ca
License: UNKNOWN
Platform: UNKNOWN
Classifier: Programming Language :: Python :: 3
Classifier: License :: OSI Approved :: MIT License
Classifier: Operating System :: OS Independent
Requires-Python: >=3.6
